LICENSE
MANIFEST.in
README.rst
setup.cfg
setup.py
tangled/__main__.py
tangled/abcs.py
tangled/commands.py
tangled/converters.py
tangled/decorators.py
tangled/registry.py
tangled/settings.py
tangled/util.py
tangled.egg-info/PKG-INFO
tangled.egg-info/SOURCES.txt
tangled.egg-info/dependency_links.txt
tangled.egg-info/entry_points.txt
tangled.egg-info/requires.txt
tangled.egg-info/top_level.txt
tangled/scripts/__init__.py
tangled/scripts/release.py
tangled/scripts/scaffold.py
tangled/scripts/shell.py
tangled/tests/__init__.py
tangled/tests/test_converters.py
tangled/tests/test_decorators.py
tangled/tests/test_registry.py
tangled/tests/test_scripts.py
tangled/tests/test_settings.py
tangled/tests/test_util.py
tangled/tests/dummy_package/__init__.py